pystuderxcom/__init__.py
pystuderxcom/api_base_async.py
pystuderxcom/api_base_sync.py
pystuderxcom/api_serial.py
pystuderxcom/api_tcp.py
pystuderxcom/api_udp.py
pystuderxcom/const.py
pystuderxcom/data.py
pystuderxcom/datapoints.py
pystuderxcom/datapoints_120v.json
pystuderxcom/datapoints_240v.json
pystuderxcom/discover_async.py
pystuderxcom/discover_sync.py
pystuderxcom/factory_async.py
pystuderxcom/factory_sync.py
pystuderxcom/families.py
pystuderxcom/messages.py
pystuderxcom/messages_en.json
pystuderxcom/protocol.py
pystuderxcom/values.py
pystuderxcom-3.2.2.dist-info/licenses/LICENSE
pystuderxcom-3.2.2.dist-info/METADATA
pystuderxcom-3.2.2.dist-info/WHEEL
pystuderxcom-3.2.2.dist-info/top_level.txt
pystuderxcom-3.2.2.dist-info/RECORD
