Metadata-Version: 2.4
Name: pystuderxcom
Version: 3.2.2
Summary: Python library to communicate with Studer-Innotec devices on the local network via Xcom protocol
Author-email: Anko Hanse <anko_hanse@hotmail.com>
Project-URL: Homepage, https://github.com/ankohanse/pystuderxcom
Project-URL: Issues, https://github.com/ankohanse/pystuderxcom/issues
Classifier: Programming Language :: Python :: 3
Classifier: License :: OSI Approved :: GNU General Public License v3 or later (GPLv3+)
Classifier: Operating System :: OS Independent
Requires-Python: >=3.8
License-File: LICENSE
Requires-Dist: httpx
Requires-Dist: asyncudp
Requires-Dist: pyserial
Requires-Dist: pyserial-asyncio
Requires-Dist: aiofiles
Requires-Dist: orjson
Provides-Extra: tests
Requires-Dist: pytest; extra == "tests"
Requires-Dist: pytest-asyncio; extra == "tests"
Dynamic: license-file
